lib/__init__.py
lib/cors.py
cors_detector-1.0.1.dist-info/METADATA
cors_detector-1.0.1.dist-info/WHEEL
cors_detector-1.0.1.dist-info/entry_points.txt
cors_detector-1.0.1.dist-info/top_level.txt
cors_detector-1.0.1.dist-info/RECORD
