Metadata-Version: 2.1
Name: cors-detector
Version: 1.0.1
Summary: The cors-detector package is used to find the vulnerable CORS domains
Home-page: UNKNOWN
Author: Hariharan
License: UNKNOWN
Keywords: cors,cors-finder,cors misconfiguration,cors exploit,cors vulnerability
Platform: UNKNOWN
Requires-Dist: colorama
Requires-Dist: requests
